{"form": [{"box": [187, 177, 637, 303], "text": "COSTCO WHOLESALE", "label": "other", "words": [{"box": [187, 177, 622, 259], "text": "COSTCO"}, {"box": [320, 268, 637, 303], "text": "WHOLESALE"}], "linking": [[]], "id": 0, "label_confidence_score": 0.9792693853378296}, {"box": [159, 347, 660, 533], "text": "Manchester WAREHOUSE 01617494365 Costco Wholesale UK Limited UK Home Office, Hartspring Lane Watford, Herts. WD25 8JS Registered in England", "label": "other", "words": [{"box": [159, 353, 320, 388], "text": "Manchester"}, {"box": [329, 351, 476, 384], "text": "WAREHOUSE"}, {"box": [484, 347, 660, 377], "text": "01617494365"}, {"box": [161, 389, 261, 426], "text": "Costco"}, {"box": [268, 388, 412, 424], "text": "Wholesale"}, {"box": [419, 386, 459, 422], "text": "UK"}, {"box": [465, 385, 581, 418], "text": "Limited"}, {"box": [161, 424, 196, 463], "text": "UK"}, {"box": [205, 424, 276, 463], "text": "Home"}, {"box": [284, 424, 394, 462], "text": "Office,"}, {"box": [402, 423, 569, 459], "text": "Hartspring"}, {"box": [576, 419, 644, 457], "text": "Lane"}, {"box": [161, 462, 289, 500], "text": "Watford,"}, {"box": [297, 461, 396, 497], "text": "Herts."}, {"box": [403, 458, 477, 494], "text": "WD25"}, {"box": [484, 455, 535, 490], "text": "8JS"}, {"box": [162, 499, 319, 533], "text": "Registered"}, {"box": [329, 495, 363, 532], "text": "in"}, {"box": [370, 494, 489, 529], "text": "England"}], "linking": [[]], "id": 1, "label_confidence_score": 0.9078456069293775}, {"box": [496, 490, 645, 523], "text": "No2635489", "label": "answer", "words": [{"box": [496, 490, 645, 523], "text": "No2635489"}], "linking": [[]], "id": 2, "label_confidence_score": 0.9969567656517029}, {"box": [160, 531, 273, 568], "text": "VAT NO:", "label": "question", "words": [{"box": [160, 533, 212, 568], "text": "VAT"}, {"box": [219, 531, 273, 568], "text": "NO:"}], "linking": [{"linking": [4, 3], "prob_score": 0.9505714073162308}], "id": 3, "label_confidence_score": 0.9961968660354614}, {"box": [281, 529, 450, 568], "text": "650 1862 52", "label": "answer", "words": [{"box": [281, 530, 332, 568], "text": "650"}, {"box": [344, 529, 409, 567], "text": "1862"}, {"box": [419, 529, 450, 566], "text": "52"}], "linking": [{"linking": [4, 3], "prob_score": 0.9505714073162308}], "id": 4, "label_confidence_score": 0.9007988572120667}, {"box": [160, 607, 231, 640], "text": "Date:", "label": "question", "words": [{"box": [160, 607, 231, 640], "text": "Date:"}], "linking": [{"linking": [6, 5], "prob_score": 0.6194476339932866}], "id": 5, "label_confidence_score": 0.9941089749336243}, {"box": [435, 600, 666, 638], "text": "22/12/17 06:43", "label": "answer", "words": [{"box": [435, 600, 572, 638], "text": "22/12/17"}, {"box": [580, 601, 666, 638], "text": "06:43"}], "linking": [{"linking": [6, 5], "prob_score": 0.6194476339932866}], "id": 6, "label_confidence_score": 0.8337460458278656}, {"box": [158, 678, 341, 715], "text": "Product name", "label": "question", "words": [{"box": [158, 678, 275, 714], "text": "Product"}, {"box": [283, 681, 341, 715], "text": "name"}], "linking": [{"linking": [8, 7], "prob_score": 0.7405453308391813}], "id": 7, "label_confidence_score": 0.9846524298191071}, {"box": [437, 676, 660, 715], "text": "PREMIUM DIESEL", "label": "answer", "words": [{"box": [437, 676, 555, 714], "text": "PREMIUM"}, {"box": [563, 677, 660, 715], "text": "DIESEL"}], "linking": [{"linking": [8, 7], "prob_score": 0.7405453308391813}], "id": 8, "label_confidence_score": 0.9894799888134003}, {"box": [156, 716, 227, 754], "text": "Pump", "label": "question", "words": [{"box": [156, 716, 227, 754], "text": "Pump"}], "linking": [{"linking": [10, 9], "prob_score": 0.9455034229230728}], "id": 9, "label_confidence_score": 0.9539815187454224}, {"box": [235, 716, 262, 754], "text": "Nr", "label": "answer", "words": [{"box": [235, 716, 262, 754], "text": "Nr"}], "linking": [{"linking": [10, 9], "prob_score": 0.9455034229230728}], "id": 10, "label_confidence_score": 0.5833618640899658}, {"box": [155, 752, 237, 786], "text": "Price", "label": "question", "words": [{"box": [155, 752, 237, 786], "text": "Price"}], "linking": [{"linking": [12, 11], "prob_score": 0.5130877391377578}], "id": 11, "label_confidence_score": 0.9461373686790466}, {"box": [519, 754, 666, 792], "text": "E/L 1. 139", "label": "answer", "words": [{"box": [519, 754, 573, 790], "text": "E/L"}, {"box": [586, 754, 612, 790], "text": "1."}, {"box": [619, 754, 666, 792], "text": "139"}], "linking": [{"linking": [12, 11], "prob_score": 0.5130877391377578}], "id": 12, "label_confidence_score": 0.9873213768005371}, {"box": [155, 789, 279, 831], "text": "Quantity", "label": "question", "words": [{"box": [155, 789, 279, 831], "text": "Quantity"}], "linking": [{"linking": [14, 13], "prob_score": 0.7174287350236429}], "id": 13, "label_confidence_score": 0.9727804064750671}, {"box": [549, 793, 669, 830], "text": "L 30. 73", "label": "answer", "words": [{"box": [549, 793, 572, 829], "text": "L"}, {"box": [586, 793, 630, 830], "text": "30."}, {"box": [637, 793, 669, 829], "text": "73"}], "linking": [{"linking": [14, 13], "prob_score": 0.7174287350236429}], "id": 14, "label_confidence_score": 0.9943585594495138}, {"box": [155, 828, 232, 865], "text": "Total", "label": "question", "words": [{"box": [155, 828, 232, 865], "text": "Total"}], "linking": [[]], "id": 15, "label_confidence_score": 0.9685018658638}, {"box": [553, 831, 665, 869], "text": "f 35.00", "label": "answer", "words": [{"box": [553, 832, 574, 866], "text": "f"}, {"box": [587, 831, 665, 869], "text": "35.00"}], "linking": [[]], "id": 16, "label_confidence_score": 0.9784516096115112}, {"box": [168, 905, 238, 943], "text": "RATE", "label": "question", "words": [{"box": [168, 905, 238, 943], "text": "RATE"}], "linking": [{"linking": [21, 17], "prob_score": 0.7939969622787478}], "id": 17, "label_confidence_score": 0.9037870168685913}, {"box": [264, 906, 545, 946], "text": "CODE VAT", "label": "question", "words": [{"box": [264, 906, 334, 944], "text": "CODE"}, {"box": [488, 909, 545, 946], "text": "VAT"}], "linking": [{"linking": [22, 18], "prob_score": 0.2686125839375865}], "id": 18, "label_confidence_score": 0.6905535459518433}, {"box": [377, 907, 444, 945], "text": "EXCL", "label": "question", "words": [{"box": [377, 907, 444, 945], "text": "EXCL"}], "linking": [[]], "id": 19, "label_confidence_score": 0.7731171250343323}, {"box": [591, 910, 652, 948], "text": "INCL", "label": "question", "words": [{"box": [591, 910, 652, 948], "text": "INCL"}], "linking": [[]], "id": 20, "label_confidence_score": 0.7140675783157349}, {"box": [153, 945, 241, 984], "text": "20. 00%", "label": "answer", "words": [{"box": [153, 945, 189, 983], "text": "20."}, {"box": [197, 946, 241, 984], "text": "00%"}], "linking": [{"linking": [21, 17], "prob_score": 0.7939969622787478}], "id": 21, "label_confidence_score": 0.8664466142654419}, {"box": [311, 946, 453, 989], "text": "2 29. 17", "label": "answer", "words": [{"box": [311, 946, 337, 988], "text": "2"}, {"box": [358, 946, 401, 989], "text": "29."}, {"box": [411, 947, 453, 989], "text": "17"}], "linking": [{"linking": [22, 18], "prob_score": 0.2686125839375865}], "id": 22, "label_confidence_score": 0.8849955995877584}, {"box": [474, 948, 654, 992], "text": "5.83 35.00", "label": "answer", "words": [{"box": [474, 948, 550, 991], "text": "5.83"}, {"box": [574, 949, 654, 992], "text": "35.00"}], "linking": [[]], "id": 23, "label_confidence_score": 0.76955646276474}]}